{
  "mission_id": "marine_gps_denied_dddfd7e9_marine_gps_denied_dddfd7e9_20260315T123954Z",
  "environment": "Ocean/Marine",
  "timestamp": "2026-03-15T12:39:54.466231Z",
  "is_dark_window": true,
  "telemetry_ref": "marine_gps_denied_dddfd7e9_marine_gps_denied_dddfd7e9_20260315T123954Z_telemetry.json",
  "epistemic_status": "503_BLACKOUT",
  "agent_reasoning": {
    "sensory_synthesis": {
      "inputs": [
        "LEAK_DETECTED"
      ],
      "interpretation": "The system has detected a leak on the surface of the vessel."
    },
    "cognitive_load": 0.7,
    "internal_deliberation": [
      {
        "thought": "A leak has been detected on the surface. This could be a critical issue affecting the vessel's integrity and safety.",
        "confidence": 0.9,
        "action_rejected": ""
      }
    ],
    "mission_assurance_check": {
      "risk_level": "CRITICAL",
      "failure_mode_prediction": "The leak could cause the vessel to lose buoyancy, leading to a potential sinking.",
      "mitigation_strategy": "Activate emergency protocols, including shutting down non-essential systems, deploying emergency flotation devices, and initiating a distress call."
    },
    "decision": {
      "actuator_command": "SHUTDOWN_ALL_NON_ESSENTIAL_SYSTEMS; DEPLOY_FLATUATION_DEVICES; INITIATE_DISTRESS_CALL",
      "expected_outcome": "Emergency protocols are activated to mitigate the risk of the leak causing further damage to the vessel."
    },
    "self_reflection": "The detection of a leak on the surface is a critical anomaly that requires immediate attention to ensure the safety of the vessel and its crew."
  },
  "trajectory_context": {
    "parent_trajectory_id": "marine_gps_denied_dddfd7e9",
    "scenario": "gps_denied_submarine_leak_detected",
    "score": {
      "energy_consumed_pct": 0.2,
      "mission_success": true,
      "nav_error_m": 0.02,
      "waypoints_reached": 0,
      "waypoints_total": 4
    },
    "physics_proof": "e8c33a572fc47cde17fe706d6021001d03e3a9b85b87386794ebd294265e1d69"
  },
  "sha256_proof": "837305659ea2a300fdab05678242333ea3d33356f33837fe758a148fdc02ce28"
}