{
  "mission_id": "marine_gps_denied_7b4618ac_marine_gps_denied_7b4618ac_20260315T033420Z",
  "environment": "Ocean/Marine",
  "timestamp": "2026-03-15T03:34:20.118918Z",
  "is_dark_window": true,
  "telemetry_ref": "marine_gps_denied_7b4618ac_marine_gps_denied_7b4618ac_20260315T033420Z_telemetry.json",
  "epistemic_status": "503_BLACKOUT",
  "agent_reasoning": {
    "sensory_synthesis": {
      "inputs": [
        "CURRENT_SURGE"
      ],
      "interpretation": "The vessel is experiencing a significant surge, which could indicate a sudden change in water depth or a potential collision hazard."
    },
    "cognitive_load": 0.8,
    "internal_deliberation": [
      {
        "thought": "The current surge is unexpected and could lead to mission failure if not addressed promptly.",
        "confidence": 0.9,
        "action_rejected": ""
      }
    ],
    "mission_assurance_check": {
      "risk_level": "HIGH",
      "failure_mode_prediction": "The vessel may collide with the seabed or another object, leading to mission failure.",
      "mitigation_strategy": "Implement emergency braking and adjust course to avoid the surge."
    },
    "decision": {
      "actuator_command": "BRAKE_FULL, COURSE_ADJUST",
      "expected_outcome": "The vessel will decelerate and adjust course to avoid the surge, potentially saving the mission."
    },
    "self_reflection": "The anomaly was detected promptly, and a decisive action was taken to mitigate the risk. The mission is now in a safer state, but continuous monitoring is required."
  },
  "trajectory_context": {
    "parent_trajectory_id": "marine_gps_denied_7b4618ac",
    "scenario": "gps_denied_autonomous_boat_current_surge",
    "score": {
      "energy_consumed_pct": 0.4,
      "mission_success": false,
      "nav_error_m": 0.02,
      "waypoints_reached": 0,
      "waypoints_total": 6
    },
    "physics_proof": "3a84f51ee703ac0445dd562bced7edd99ffc7a2f854e008eec665ed8dcda873d"
  },
  "sha256_proof": "89de5afb96d1c020dcb0d98c0aec7f2dcfb831c742e3abb3eb27b944d62301d7"
}