{
  "mission_id": "marine_gps_denied_c6297ec6_marine_gps_denied_c6297ec6_20260315T105726Z",
  "environment": "Ocean/Marine",
  "timestamp": "2026-03-15T10:57:26.318598Z",
  "is_dark_window": true,
  "telemetry_ref": "marine_gps_denied_c6297ec6_marine_gps_denied_c6297ec6_20260315T105726Z_telemetry.json",
  "epistemic_status": "503_BLACKOUT",
  "agent_reasoning": {
    "sensory_synthesis": {
      "inputs": [
        "battery level is high",
        "current readings are within normal range",
        "depth is stable",
        "drift is within acceptable limits",
        "navigation error is minimal",
        "position is accurate",
        "velocity is within expected range",
        "waypoint is at 0"
      ],
      "interpretation": "The system appears to be functioning normally with no significant anomalies detected. The battery is at a healthy level, and all sensor readings are within expected parameters."
    },
    "cognitive_load": 0.1,
    "internal_deliberation": [
      {
        "thought": "The mission appears to be proceeding as expected with no critical issues detected.",
        "confidence": 0.9,
        "action_rejected": ""
      }
    ],
    "mission_assurance_check": {
      "risk_level": "LOW",
      "failure_mode_prediction": "No immediate failure modes predicted based on current telemetry.",
      "mitigation_strategy": "Continue monitoring the system for any changes in telemetry."
    },
    "decision": {
      "actuator_command": "continue mission",
      "expected_outcome": "The mission will continue as planned without any intervention."
    },
    "self_reflection": "The system is performing within normal parameters, and there are no indications of any issues that would require intervention. The mission should be allowed to continue."
  },
  "trajectory_context": {
    "parent_trajectory_id": "marine_gps_denied_c6297ec6",
    "scenario": "gps_denied_submarine_none",
    "score": {
      "energy_consumed_pct": 1.2,
      "mission_success": false,
      "nav_error_m": 0.02,
      "waypoints_reached": 0,
      "waypoints_total": 4
    },
    "physics_proof": "10203e946c7bdae2fecfac7214f6e65004ce3323ac352079573dee55b3f76e9d"
  },
  "sha256_proof": "e8b7a74051429131346a2718e0e86351d84d249686806c277923df6b0132b0b4"
}