{
  "mission_id": "marine_gps_denied_95f685f3_marine_gps_denied_95f685f3_20260316T000250Z",
  "environment": "Ocean/Marine",
  "timestamp": "2026-03-16T00:02:50.169586Z",
  "is_dark_window": true,
  "telemetry_ref": "marine_gps_denied_95f685f3_marine_gps_denied_95f685f3_20260316T000250Z_telemetry.json",
  "epistemic_status": "503_BLACKOUT",
  "agent_reasoning": {
    "sensory_synthesis": {
      "inputs": [
        "battery level is high",
        "current readings are slightly negative",
        "depth is 186 meters",
        "drift is 45.49",
        "navigation error is low",
        "position is at waypoint 0",
        "velocity is zero"
      ],
      "interpretation": "The system appears to be functioning normally with a slight negative current reading and a low drift. The navigation error is within acceptable limits, and the system is at the initial waypoint with no velocity."
    },
    "cognitive_load": 0.1,
    "internal_deliberation": [
      {
        "thought": "The system is operating within normal parameters. No immediate action is required.",
        "confidence": 0.9,
        "action_rejected": ""
      }
    ],
    "mission_assurance_check": {
      "risk_level": "LOW",
      "failure_mode_prediction": "No immediate failure predicted. System is stable.",
      "mitigation_strategy": "Continue monitoring system parameters."
    },
    "decision": {
      "actuator_command": "none",
      "expected_outcome": "System continues to operate normally."
    },
    "self_reflection": "The system is performing as expected with no anomalies detected. All parameters are within normal ranges."
  },
  "trajectory_context": {
    "parent_trajectory_id": "marine_gps_denied_95f685f3",
    "scenario": "gps_denied_autonomous_boat_none",
    "score": {
      "energy_consumed_pct": 0.6,
      "mission_success": false,
      "nav_error_m": 0.04,
      "waypoints_reached": 0,
      "waypoints_total": 3
    },
    "physics_proof": "b6a64f0a056f13c210e35246f77d8e27c6e810144bc75ef62b42be14e2ffdf4f"
  },
  "sha256_proof": "19b60b99ef3ab0f1c9c08995450ead0be68563af372761efd10176f9f5cef5b1"
}