{
  "mission_id": "marine_gps_denied_b9e126c9_marine_gps_denied_b9e126c9_20260315T155455Z",
  "environment": "Ocean/Marine",
  "timestamp": "2026-03-15T15:54:55.022699Z",
  "is_dark_window": true,
  "telemetry_ref": "marine_gps_denied_b9e126c9_marine_gps_denied_b9e126c9_20260315T155455Z_telemetry.json",
  "epistemic_status": "503_BLACKOUT",
  "agent_reasoning": {
    "sensory_synthesis": {
      "inputs": [
        "battery level is high",
        "current readings are within normal range",
        "depth is shallow",
        "drift is moderate",
        "navigation error is low",
        "position and time data are accurate",
        "velocity is slow",
        "waypoint is at the start"
      ],
      "interpretation": "The system appears to be functioning normally with no immediate threats or anomalies detected. The battery is healthy, the current is stable, the depth is within safe limits, and the navigation is on track. The system is ready to continue the mission."
    },
    "cognitive_load": 0.1,
    "internal_deliberation": [
      {
        "thought": "The system is operating within normal parameters. No immediate action is required.",
        "confidence": 0.9,
        "action_rejected": ""
      }
    ],
    "mission_assurance_check": {
      "risk_level": "LOW",
      "failure_mode_prediction": "No significant issues detected. The system is expected to continue operating as intended.",
      "mitigation_strategy": "No action needed at this time."
    },
    "decision": {
      "actuator_command": "continue mission",
      "expected_outcome": "The mission will continue as planned without interruption."
    },
    "self_reflection": "The system has detected no anomalies and is operating within normal parameters. The mission is proceeding as expected."
  },
  "trajectory_context": {
    "parent_trajectory_id": "marine_gps_denied_b9e126c9",
    "scenario": "gps_denied_autonomous_boat_none",
    "score": {
      "energy_consumed_pct": 0.6,
      "mission_success": false,
      "nav_error_m": 0.03,
      "waypoints_reached": 0,
      "waypoints_total": 6
    },
    "physics_proof": "1a93495259a3399c77e45c286fe9afa382fc3ace65d3e29de9e4c6c9dfbaa3db"
  },
  "sha256_proof": "15eb0f7c8bc0c497856efdf1ac352f013105267c6eac327a3dcd12f1b3423dd5"
}