{
  "mission_id": "marine_gps_denied_6a08230c_marine_gps_denied_6a08230c_20260315T000223Z",
  "environment": "Ocean/Marine",
  "timestamp": "2026-03-15T00:02:23.237103Z",
  "is_dark_window": true,
  "telemetry_ref": "marine_gps_denied_6a08230c_marine_gps_denied_6a08230c_20260315T000223Z_telemetry.json",
  "epistemic_status": "503_BLACKOUT",
  "agent_reasoning": {
    "sensory_synthesis": {
      "inputs": [
        "battery level is high",
        "current readings are normal",
        "depth is shallow",
        "drift is moderate",
        "navigation error is low",
        "attitude is stable",
        "temperature is normal",
        "velocity is slow",
        "waypoint is at the start"
      ],
      "interpretation": "The system appears to be functioning normally with no immediate threats or anomalies detected. The battery is well-charged, and the vehicle is maintaining a stable position in the water. The navigation error is within acceptable limits, and the vehicle is not drifting excessively. The current conditions suggest that the mission is proceeding as expected."
    },
    "cognitive_load": 0.1,
    "internal_deliberation": [
      {
        "thought": "The system is performing within expected parameters. No immediate action is required.",
        "confidence": 0.9,
        "action_rejected": ""
      }
    ],
    "mission_assurance_check": {
      "risk_level": "LOW",
      "failure_mode_prediction": "No significant issues detected. The system is stable and performing as expected.",
      "mitigation_strategy": "Continue monitoring the system for any changes in performance."
    },
    "decision": {
      "actuator_command": "continue mission",
      "expected_outcome": "The mission will continue as planned without any changes."
    },
    "self_reflection": "The system is currently stable and performing within expected parameters. No immediate action is required. The mission is proceeding as planned."
  },
  "trajectory_context": {
    "parent_trajectory_id": "marine_gps_denied_6a08230c",
    "scenario": "gps_denied_submarine_none",
    "score": {
      "energy_consumed_pct": 0.4,
      "mission_success": false,
      "nav_error_m": 0.04,
      "waypoints_reached": 0,
      "waypoints_total": 6
    },
    "physics_proof": "22aa71cf80e175ef75b671a2201564f746e46495e5ac2938ad02b542633b86c4"
  },
  "sha256_proof": "b2dfee2c3f33e1b0202840403f44e46d472129958f06f01d9d5078c01c16cbb8"
}