{
  "mission_id": "marine_gps_denied_973335dc_marine_gps_denied_973335dc_20260315T042645Z",
  "environment": "Ocean/Marine",
  "timestamp": "2026-03-15T04:26:45.524078Z",
  "is_dark_window": true,
  "telemetry_ref": "marine_gps_denied_973335dc_marine_gps_denied_973335dc_20260315T042645Z_telemetry.json",
  "epistemic_status": "503_BLACKOUT",
  "agent_reasoning": {
    "sensory_synthesis": {
      "inputs": [
        "battery_degradation",
        "low_battery"
      ],
      "interpretation": "The battery level is critically low, indicating that the system is running on minimal power. This could lead to a complete system failure if not addressed promptly."
    },
    "cognitive_load": 0.8,
    "internal_deliberation": [
      {
        "thought": "The battery is at 59.5%, which is dangerously low. Immediate action is required to prevent a complete system failure.",
        "confidence": 0.9,
        "action_rejected": ""
      }
    ],
    "mission_assurance_check": {
      "risk_level": "CRITICAL",
      "failure_mode_prediction": "The system may fail completely within the next few minutes, leading to mission failure.",
      "mitigation_strategy": "Initiate emergency power management protocols and attempt to land or return to a safe location."
    },
    "decision": {
      "actuator_command": "initiate_emergency_power_management",
      "expected_outcome": "The system will attempt to conserve power and initiate a safe return or landing procedure."
    },
    "self_reflection": "The critical battery level indicates a severe failure mode. Immediate action is necessary to prevent a complete system failure and ensure the safety of the mission."
  },
  "trajectory_context": {
    "parent_trajectory_id": "marine_gps_denied_973335dc",
    "scenario": "gps_denied_submarine_battery_degradation",
    "score": {
      "energy_consumed_pct": 40.5,
      "mission_success": false,
      "nav_error_m": 0.01,
      "waypoints_reached": 0,
      "waypoints_total": 3
    },
    "physics_proof": "256ad7dba9fd712bc946538c29df6f3ac4c6a96d0dd2a7ad9bb7cb31c05e15f2"
  },
  "sha256_proof": "f5aca4720e49127013906531bbda1bfea01e63ec352e009b58b674ced3c4255c"
}