{
  "mission_id": "marine_gps_denied_850bde51_marine_gps_denied_850bde51_20260315T191353Z",
  "environment": "Ocean/Marine",
  "timestamp": "2026-03-15T19:13:53.249976Z",
  "is_dark_window": true,
  "telemetry_ref": "marine_gps_denied_850bde51_marine_gps_denied_850bde51_20260315T191353Z_telemetry.json",
  "epistemic_status": "503_BLACKOUT",
  "agent_reasoning": {
    "sensory_synthesis": {
      "inputs": [
        "CURRENT_SURGE"
      ],
      "interpretation": "The vessel is experiencing a significant surge, which could indicate a sudden change in water conditions or an issue with the propulsion system."
    },
    "cognitive_load": 0.7,
    "internal_deliberation": [
      {
        "thought": "The current surge could lead to a loss of control if not managed properly.",
        "confidence": 0.8,
        "action_rejected": ""
      }
    ],
    "mission_assurance_check": {
      "risk_level": "MEDIUM",
      "failure_mode_prediction": "The surge could cause the vessel to drift off course or lose control, potentially leading to mission failure.",
      "mitigation_strategy": "Implement emergency braking and adjust course to stabilize the vessel."
    },
    "decision": {
      "actuator_command": "apply emergency braking and adjust course",
      "expected_outcome": "Stabilize the vessel and maintain control to complete the mission."
    },
    "self_reflection": "The current surge is a critical anomaly that requires immediate attention to ensure the mission can be completed safely."
  },
  "trajectory_context": {
    "parent_trajectory_id": "marine_gps_denied_850bde51",
    "scenario": "gps_denied_submarine_current_surge",
    "score": {
      "energy_consumed_pct": 0.8,
      "mission_success": false,
      "nav_error_m": 0.02,
      "waypoints_reached": 0,
      "waypoints_total": 3
    },
    "physics_proof": "4e81b661158becaca942305e57637e9c273d9942e26df5fe302a4c3ed45eca4f"
  },
  "sha256_proof": "ed2dadee44b7e18373eef1e3a23084178f87f89b07d40f80950d554c98a89285"
}